socialmediaAPI/__init__.py
socialmediaAPI/socialmedia.py
socialmediaapi-0.0.2.dist-info/METADATA
socialmediaapi-0.0.2.dist-info/WHEEL
socialmediaapi-0.0.2.dist-info/top_level.txt
socialmediaapi-0.0.2.dist-info/RECORD
