Metadata-Version: 2.1
Name: socialmediaapi
Version: 0.0.2
Summary: Basic Social Media API
Home-page: UNKNOWN
Author: Madahsm (Ahmed Hashim)
Author-email: <i00oomada@gmail.com>
License: UNKNOWN
Keywords: python,facebook
Platform: UNKNOWN
Classifier: Development Status :: 1 - Planning
Classifier: Intended Audience :: Developers
Classifier: Programming Language :: Python :: 3
Classifier: Operating System :: Unix
Classifier: Operating System :: MacOS :: MacOS X
Classifier: Operating System :: Microsoft :: Windows
Requires-Dist: requests
